datascientist/__init__.py
datascientist/connections/__init__.py
datascientist/connections/rsconnect.py
datascientist/jobs/__init__.py
datascientist/jobs/training.py
datascientist/special/__init__.py
datascientist/special/s3session.py
datascientist/workflow/__init__.py
datascientist/workflow/tracker.py
datascientist-0.2.7.dist-info/METADATA
datascientist-0.2.7.dist-info/WHEEL
datascientist-0.2.7.dist-info/top_level.txt
datascientist-0.2.7.dist-info/RECORD
