Metadata-Version: 2.1
Name: datascientist
Version: 0.2.7
Summary: A light set of enablers based on Cloudframe's proprietary data science codebase.
Home-page: https://github.com/cloudframe/datascientist
Author: Cloudframe Analytics
Author-email: info@cloudframe.io
License: MIT
Platform: UNKNOWN
Classifier: License :: OSI Approved :: MIT License
Classifier: Programming Language :: Python :: 3
Classifier: Programming Language :: Python :: 3.7
Requires-Dist: pandas
Requires-Dist: numpy
Requires-Dist: boto3
Requires-Dist: psycopg2-binary
Requires-Dist: PyYAML
